LICENSE
THERMO_LICENSE
simsi_transfer/__init__.py
simsi_transfer/__main__.py
simsi_transfer/command_line_interface.py
simsi_transfer/evidence.py
simsi_transfer/main.py
simsi_transfer/maracluster.py
simsi_transfer/maxquant.py
simsi_transfer/merging_functions.py
simsi_transfer/simsi_output.py
simsi_transfer/thermo_raw.py
simsi_transfer/tmt_processing.py
simsi_transfer/transfer.py
simsi_transfer/utils/ThermoRawFileParser/AWS.Logger.Core.dll
simsi_transfer/utils/ThermoRawFileParser/AWS.Logger.Core.pdb
simsi_transfer/utils/ThermoRawFileParser/AWSSDK.CloudWatchLogs.dll
simsi_transfer/utils/ThermoRawFileParser/AWSSDK.CloudWatchLogs.pdb
simsi_transfer/utils/ThermoRawFileParser/AWSSDK.Core.dll
simsi_transfer/utils/ThermoRawFileParser/AWSSDK.Core.pdb
simsi_transfer/utils/ThermoRawFileParser/AWSSDK.S3.dll
simsi_transfer/utils/ThermoRawFileParser/AWSSDK.S3.pdb
simsi_transfer/utils/ThermoRawFileParser/IronSnappy.dll
simsi_transfer/utils/ThermoRawFileParser/LICENSE
simsi_transfer/utils/ThermoRawFileParser/MathNet.Numerics.dll
simsi_transfer/utils/ThermoRawFileParser/Mono.Options.dll
simsi_transfer/utils/ThermoRawFileParser/NJsonSchema.dll
simsi_transfer/utils/ThermoRawFileParser/NUnit3.TestAdapter.dll
simsi_transfer/utils/ThermoRawFileParser/NUnit3.TestAdapter.pdb
simsi_transfer/utils/ThermoRawFileParser/Namotion.Reflection.dll
simsi_transfer/utils/ThermoRawFileParser/Newtonsoft.Json.dll
simsi_transfer/utils/ThermoRawFileParser/OpenMcdf.Extensions.dll
simsi_transfer/utils/ThermoRawFileParser/OpenMcdf.dll
simsi_transfer/utils/ThermoRawFileParser/Parquet.dll
simsi_transfer/utils/ThermoRawFileParser/System.Buffers.dll
simsi_transfer/utils/ThermoRawFileParser/System.IO.FileSystem.AccessControl.dll
simsi_transfer/utils/ThermoRawFileParser/System.Memory.dll
simsi_transfer/utils/ThermoRawFileParser/System.Numerics.Vectors.dll
simsi_transfer/utils/ThermoRawFileParser/System.Runtime.CompilerServices.Unsafe.dll
simsi_transfer/utils/ThermoRawFileParser/System.Security.AccessControl.dll
simsi_transfer-0.8.0.dist-info/LICENSE
simsi_transfer-0.8.0.dist-info/METADATA
simsi_transfer-0.8.0.dist-info/WHEEL
simsi_transfer-0.8.0.dist-info/RECORD
