Metadata-Version: 2.1
Name: simsi_transfer
Version: 0.8.0
Summary: Software-assisted reduction of missing values in phosphoproteomics and proteomics isobaric labeling data using MS2 spectrum clustering
Home-page: https://github.com/kusterlab/SIMSI-Transfer
License: Apache-2.0
Keywords: mass spectrometry,missing values,clustering,proteomics,quantification
Author: Firas Hamood
Author-email: firas.hamood@tum.de
Requires-Python: >=3.8,<4.0
Classifier: License :: OSI Approved :: Apache Software License
Classifier: Programming Language :: Python :: 3
Classifier: Programming Language :: Python :: 3.8
Classifier: Programming Language :: Python :: 3.9
Classifier: Programming Language :: Python :: 3.10
Classifier: Programming Language :: Python :: 3.11
Classifier: Programming Language :: Python :: 3.12
Provides-Extra: gui
Requires-Dist: job-pool (>=0.3.0)
Requires-Dist: lxml (>=4.8.0,<5.0.0)
Requires-Dist: numpy (>=1.18.1)
Requires-Dist: pandas (>=1.4.0)
Requires-Dist: pyarrow (==19.0.1)
Requires-Dist: pyqt5 (==5.15.7) ; extra == "gui"
Requires-Dist: pyqt5-qt5 (==5.15.2) ; extra == "gui"
Requires-Dist: pyteomics (>=4.5.3,<5.0.0)
Requires-Dist: tqdm (>=4.66.1,<5.0.0)
Project-URL: Repository, https://github.com/kusterlab/SIMSI-Transfer
